infinite_sets/__init__.py
infinite_sets/infinite_sets.py
infinite_sets/py.typed
infinite_sets-1.0.2.dist-info/LICENSE
infinite_sets-1.0.2.dist-info/METADATA
infinite_sets-1.0.2.dist-info/WHEEL
infinite_sets-1.0.2.dist-info/top_level.txt
infinite_sets-1.0.2.dist-info/RECORD
