Metadata-Version: 2.1
Name: infinite-sets
Version: 1.0.2
Summary: Code to express the universal set and set complements in a pythonic manner
Home-page: http://gitlab.com/alexjbinnie/infinite-sets
Author: Alex Jamieson-Binnie
Author-email: alexjbinnie@alexjbinnie.com
License: MIT
Project-URL: Bug Tracker, https://gitlab.com/alexjbinnie/infinite-sets/-/issues
Platform: UNKNOWN
Classifier: Development Status :: 5 - Production/Stable
Classifier: Programming Language :: Python :: 3
Classifier: Intended Audience :: Developers
Classifier: License :: OSI Approved :: MIT License
Classifier: Natural Language :: English
Classifier: Topic :: Utilities
Classifier: Typing :: Typed
Requires-Python: >=3.6
Requires-Dist: typing-extensions
